simplespark/__init__.py
simplespark/environment/__init__.py
simplespark/environment/build.py
simplespark/environment/config.py
simplespark/environment/tasks.py
simplespark/environment/templates.py
simplespark/main.py
simplespark/main_binary.py
simplespark/utils/__init__.py
simplespark/utils/maven.py
simplespark/utils/network.py
simplespark/utils/ssh.py
simplespark-0.2.1.dist-info/LICENSE
simplespark-0.2.1.dist-info/METADATA
simplespark-0.2.1.dist-info/WHEEL
simplespark-0.2.1.dist-info/entry_points.txt
simplespark-0.2.1.dist-info/RECORD
