Metadata-Version: 2.3
Name: simplespark
Version: 0.2.1
Summary: Spark environment manager and job orchestrator
Author: Ross Palmer
Author-email: rossbpalmer@gmail.com
Requires-Python: >=3.11,<3.14
Classifier: Programming Language :: Python :: 3
Classifier: Programming Language :: Python :: 3.11
Classifier: Programming Language :: Python :: 3.12
Classifier: Programming Language :: Python :: 3.13
Requires-Dist: paramiko (==3.5.1)
Requires-Dist: pyinstaller (==6.12.0)
Requires-Dist: typer (>=0.15.1,<0.16.0)
Project-URL: Homepage, https://github.com/rosspalmer/Simple-Spark
